thedoorman/__init__.py
thedoorman/plugins.py
thedoorman/run.py
thedoorman/slackbot_settings.py
thedoorman-0.1.1.data/data/license/LICENSE
thedoorman-0.1.1.dist-info/DESCRIPTION.rst
thedoorman-0.1.1.dist-info/METADATA
thedoorman-0.1.1.dist-info/RECORD
thedoorman-0.1.1.dist-info/WHEEL
thedoorman-0.1.1.dist-info/metadata.json
thedoorman-0.1.1.dist-info/top_level.txt
