Metadata-Version: 2.0
Name: thedoorman
Version: 0.1.1
Summary: Remote Doorman
Home-page: https://github.com/FocusedSupport/thedoorman
Author: Dave Ehrenberger
Author-email: dave.ehrenberger@focusedsupport.com
License: MIT License
Requires-Dist: slackbot
